circuitpython_tool/__init__.py
circuitpython_tool/async_iter.py
circuitpython_tool/dirs.py
circuitpython_tool/iter.py
circuitpython_tool/render.py
circuitpython_tool/request_cache.py
circuitpython_tool/cli/__init__.py
circuitpython_tool/cli/commands.py
circuitpython_tool/cli/decorators.py
circuitpython_tool/cli/params.py
circuitpython_tool/cli/shared_state.py
circuitpython_tool/cli/uf2_commands.py
circuitpython_tool/fs/__init__.py
circuitpython_tool/fs/fs.py
circuitpython_tool/fs/inotify.py
circuitpython_tool/hw/__init__.py
circuitpython_tool/hw/device.py
circuitpython_tool/hw/fake_device.py
circuitpython_tool/hw/partition.py
circuitpython_tool/hw/query.py
circuitpython_tool/hw/real_device.py
circuitpython_tool/hw/shell.py
circuitpython_tool/hw/udev.py
circuitpython_tool/hw/uf2_device.py
circuitpython_tool/static/README.md
circuitpython_tool/static/flash_nuke.uf2
circuitpython_tool/static/uf2_exit.uf2
circuitpython_tool/tools/command_info.py
circuitpython_tool/tools/inotify_cli.py
circuitpython_tool/tools/shell_completer.py
circuitpython_tool/tools/sphinx_docs.py
circuitpython_tool/uf2/__init__.py
circuitpython_tool/uf2/block.py
circuitpython_tool/uf2/board.py
circuitpython_tool-0.11.0.dist-info/METADATA
circuitpython_tool-0.11.0.dist-info/WHEEL
circuitpython_tool-0.11.0.dist-info/entry_points.txt
circuitpython_tool-0.11.0.dist-info/licenses/LICENSE
circuitpython_tool-0.11.0.dist-info/RECORD
