Metadata-Version: 2.1
Name: circuitpython-tool
Version: 0.11.0
Summary: Command-line tool for interfacing with CircuitPython devices.
Project-URL: Source code, https://github.com/dhrosa/circuitpython_tool
Author-email: Diony Rosa <dhrosa+dev@gmail.com>
License-Expression: MIT
License-File: LICENSE
Keywords: adafruit,circuitpython,microcontroller,rp2040
Requires-Python: >=3.10
Requires-Dist: click
Requires-Dist: humanize
Requires-Dist: platformdirs
Requires-Dist: readchar
Requires-Dist: rich
Requires-Dist: rich-click
Requires-Dist: tomlkit
